<?xml version="1.0" encoding="utf-8"?>
<Screen name="Main Menu">
  <GameObjects>
    <GameObject layer="GUI" name="Title" position="0.5%, 0.8%, 0">
      <Components>
        <TextRenderer font_height="32" horizontal_alignment="centre">
          <Lines>
            <Line>Under Siege</Line>
          </Lines>
        </TextRenderer>
      </Components>
    </GameObject>
    <GameObject layer="GUI" name="Background" position="0.5%, 0.5%, 0">
      <Components>
        <SpriteRenderer sprite="Backgrounds\MainMenuBackground.png"/>
      </Components>
    </GameObject>
    <GameObject layer="GUI" name="PlayButton">
      <Components>
        <Button text="Play" font_height="24">
          <LeftClickCallbacks>
            <Callback name="KillScreen" arg="PersistentStartupAndMainMenu"/>
          </LeftClickCallbacks>
        </Button>
      </Components>
    </GameObject>
    <GameObject layer="GUI" name="OptionsButton">
      <Components>
        <Button text="Options" font_height="24">
          <LeftClickCallbacks>
            <Callback name="TransitionToScreen" arg="Screens\OptionsScreen.xml"/>
          </LeftClickCallbacks>
        </Button>
      </Components>
    </GameObject>
    <GameObject layer="GUI" name="ExitButton">
      <Components>
        <Button text="Exit" font_height="24">
          <LeftClickCallbacks>
            <Callback name="ExitGame"/>
          </LeftClickCallbacks>
        </Button>
      </Components>
    </GameObject>
    <GameObject layer="GUI" position="0.5%, 0" name="LayoutStackPanel">
      <Components>
        <StackPanel orientation="vertical" vertical_alignment="centre" padding="20">
          <Children>
            <Child name="PlayButton"/>
            <Child name="OptionsButton"/>
            <Child name="ExitButton"/>
          </Children>
        </StackPanel>
      </Components>
    </GameObject>
  </GameObjects>
</Screen>